spatial_ops/__init__.py
spatial_ops/version.py
spatial_ops/cli/__init__.py
spatial_ops/cli/main.py
spatial_ops-0.1.0.dist-info/AUTHORS.rst
spatial_ops-0.1.0.dist-info/LICENSE.txt
spatial_ops-0.1.0.dist-info/METADATA
spatial_ops-0.1.0.dist-info/WHEEL
spatial_ops-0.1.0.dist-info/entry_points.txt
spatial_ops-0.1.0.dist-info/top_level.txt
spatial_ops-0.1.0.dist-info/RECORD
