Metadata-Version: 2.1
Name: spatial-ops
Version: 0.1.0
Summary: spatial ops is libraray for spatial transcritomics
Home-page: https://github.com/DerThorsten/spatial_ops
Author: Thorsten Beier
Author-email: derthorstenbeier@gmail.com
License: UNKNOWN
Keywords: spatial_ops
Platform: UNKNOWN
Classifier: Development Status :: 2 - Pre-Alpha
Classifier: Intended Audience :: Developers
Classifier: Natural Language :: English
Classifier: Programming Language :: Python :: 3.6
Classifier: Programming Language :: Python :: 3.7
Classifier: Programming Language :: Python :: 3.8
Requires-Dist: click (>=6.0)
